certificate_search-0.3.dist-info/METADATA
certificate_search-0.3.dist-info/RECORD
certificate_search-0.3.dist-info/WHEEL
certificate_search-0.3.dist-info/top_level.txt
crt/__init__.py
crt/search.py
crt/sites/__init__.py
crt/sites/crtsh.py
