Metadata-Version: 2.1
Name: certificate-search
Version: 0.3
Summary: Certificate Transparency search
Home-page: https://github.com/huydhn/crt-search
Author: Huy Do
Author-email: huydhn@gmail.com
License: MIT
Platform: UNKNOWN
Classifier: Programming Language :: Python :: 3
Classifier: License :: OSI Approved :: MIT License
Classifier: Operating System :: OS Independent
Requires-Dist: requests
Requires-Dist: cryptography
